fir/__init__.py
fir/cmd/__init__.py
fir/cmd/base_commands.py
fir/cmd/builder/__init__.py
fir/cmd/builder/arg_parser.py
fir/cmd/config_commands.py
fir/cmd/profile_commands.py
fir/cmd/set_commands.py
fir/cmd/status_commands.py
fir/config/__init__.py
fir/config/env_dev.py
fir/config/env_prod.py
fir/context.py
fir/data/__init__.py
fir/data/defaults.py
fir/data/profile.py
fir/data/settings.py
fir/types/__init__.py
fir/types/config_options.py
fir/types/dtos.py
fir/types/parameters.py
fir/utils/__init__.py
fir/utils/args.py
fir/utils/dates.py
fir/utils/files.py
fir/utils/logging/__init__.py
fir/utils/logging/logger.py
fir/utils/logging/profile_logging.py
fir/utils/parse.py
weavc_fir-0.1.0a5.dist-info/METADATA
weavc_fir-0.1.0a5.dist-info/WHEEL
weavc_fir-0.1.0a5.dist-info/entry_points.txt
weavc_fir-0.1.0a5.dist-info/RECORD
