Metadata-Version: 2.1
Name: weavc-fir
Version: 0.1.0a5
Summary: 
License: MIT
Author: weavc
Author-email: chrisweaver1@pm.me
Requires-Python: >=3.11,<4.0
Classifier: License :: OSI Approved :: MIT License
Classifier: Programming Language :: Python :: 3
Classifier: Programming Language :: Python :: 3.11
Classifier: Programming Language :: Python :: 3.12
Requires-Dist: argcomplete (>=3.1.6,<4.0.0)
Requires-Dist: marshmallow (>=3.20.1,<3.21.0)
Requires-Dist: python-slugify (>=8.0.1,<9.0.0)
Requires-Dist: shortuuid (>=1.0.11,<2.0.0)
Requires-Dist: tabulate (>=0.9.0,<0.10.0)
Requires-Dist: termcolor (>=2.3.0,<3.0.0)
Requires-Dist: tomli-w (>=1.0.0,<2.0.0)
